paig_authorizer_core/__init__.py
paig_authorizer_core/async_base_paig_authorizer.py
paig_authorizer_core/async_paig_authorizer.py
paig_authorizer_core/base_paig_authorizer.py
paig_authorizer_core/constants.py
paig_authorizer_core/paig_authorizer.py
paig_authorizer_core/filter/__init__.py
paig_authorizer_core/filter/base_metadata_filter_criteria_creator.py
paig_authorizer_core/filter/base_vector_db_filter_creator.py
paig_authorizer_core/filter/milvus_filter_creator.py
paig_authorizer_core/filter/opensearch_filter_creator.py
paig_authorizer_core/models/__init__.py
paig_authorizer_core/models/data_models.py
paig_authorizer_core/models/request_models.py
paig_authorizer_core/models/response_models.py
paig_authorizer_core/utils/__init__.py
paig_authorizer_core/utils/authorizer_response_utils.py
paig_authorizer_core/utils/authorizer_utils.py
paig_authorizer_core-0.0.3.dist-info/METADATA
paig_authorizer_core-0.0.3.dist-info/WHEEL
paig_authorizer_core-0.0.3.dist-info/RECORD
