Metadata-Version: 2.4
Name: paig-authorizer-core
Version: 0.0.3
Summary: PAIG Authorizer Core
Project-URL: Homepage, https://github.com/privacera/paig
Project-URL: Bug Tracker, https://github.com/privacera/paig/issues
License:                                  Apache License
Keywords: Authorizer,Governance,PAIG,Privacy,Security
Classifier: License :: Other/Proprietary License
Classifier: Operating System :: OS Independent
Classifier: Programming Language :: Python :: 3
Requires-Python: >=3.10
Requires-Dist: pydantic>=2.9.2
Provides-Extra: dev
Requires-Dist: pytest; extra == 'dev'
Requires-Dist: pytest-asyncio; extra == 'dev'
Requires-Dist: pytest-cov; extra == 'dev'
Requires-Dist: pytest-mock; extra == 'dev'
